beancount_data/__init__.py
beancount_data/data_types.py
beancount_data-3.0.2.dist-info/LICENSE
beancount_data-3.0.2.dist-info/METADATA
beancount_data-3.0.2.dist-info/WHEEL
beancount_data-3.0.2.dist-info/RECORD
