Metadata-Version: 2.1
Name: beancount-data
Version: 3.0.2
Summary: Pydantic data models for exporting Beancount data
License: MIT
Author: Fang-Pen Lin
Author-email: fangpen@launchplatform.com
Requires-Python: >=3.9,<4.0
Classifier: License :: OSI Approved :: MIT License
Classifier: Programming Language :: Python :: 3
Classifier: Programming Language :: Python :: 3.9
Classifier: Programming Language :: Python :: 3.10
Classifier: Programming Language :: Python :: 3.11
Classifier: Programming Language :: Python :: 3.12
Requires-Dist: pydantic (>=2.0.0,<3.0.0)
